work_calendar/__init__.py
work_calendar/total.json
work_calendar-1.1.0.dist-info/LICENSE
work_calendar-1.1.0.dist-info/METADATA
work_calendar-1.1.0.dist-info/WHEEL
work_calendar-1.1.0.dist-info/RECORD
