Metadata-Version: 2.3
Name: work-calendar
Version: 1.1.0
Summary: Determines if a day is a working day in Russia
Keywords: utility,python,official,work,calendar,Russia
Author: Polyrom
Author-email: roman61394@gmail.com
Requires-Python: >=3.10,<4.0
Classifier: Programming Language :: Python :: 3
Classifier: Programming Language :: Python :: 3.10
Classifier: Programming Language :: Python :: 3.11
Classifier: Programming Language :: Python :: 3.12
Classifier: Programming Language :: Python :: 3.13
Project-URL: Documentation, https://github.com/Polyrom/work-calendar
Project-URL: Homepage, https://github.com/Polyrom/work-calendar
Project-URL: Repository, https://github.com/Polyrom/work-calendar.git
